setup.py
lk2000_distributions/Binomialdistribution.py
lk2000_distributions/Gaussiandistribution.py
lk2000_distributions/Generaldistribution.py
lk2000_distributions/__init__.py
lk2000_distributions.egg-info/PKG-INFO
lk2000_distributions.egg-info/SOURCES.txt
lk2000_distributions.egg-info/dependency_links.txt
lk2000_distributions.egg-info/not-zip-safe
lk2000_distributions.egg-info/top_level.txt