Metadata-Version: 1.0
Name: lk2000-distributions
Version: 0.1
Summary: Gaussian and Binomial distributions
Home-page: UNKNOWN
Author: Thien Le
Author-email: thienlk2000@gmail.com
License: UNKNOWN
Platform: UNKNOWN
